shreducer/__init__.py
shreducer/generators.py
shreducer/grammar.py
shreducer/parse_tree.py
shreducer/parser.py
shreducer/tokenizers.py
shreducer/examples/__init__.py
shreducer/examples/elasticsearch_dsl_py_expressions.py
shreducer/examples/two_pass_processing.py
shreducer/examples/generators/__init__.py
shreducer/examples/generators/arithmetic.py
shreducer/examples/grammars/__init__.py
shreducer/examples/grammars/better_arithmetics.py
shreducer/examples/grammars/better_filters.py
shreducer/examples/grammars/dictionary.py
shreducer/examples/grammars/filter_expressions.py
shreducer/examples/grammars/list_grammar.py
shreducer/examples/grammars/plus_minus_arithmetics.py
shreducer/examples/grammars/type_hints.py
shreducer-1.0.1.dist-info/METADATA
shreducer-1.0.1.dist-info/RECORD
shreducer-1.0.1.dist-info/WHEEL
shreducer-1.0.1.dist-info/top_level.txt
shreducer_examples/__init__.py
shreducer_examples/elasticsearch_dsl_py_expressions.py
shreducer_examples/two_pass_processing.py
shreducer_examples/generators/__init__.py
shreducer_examples/generators/arithmetic.py
shreducer_examples/grammars/__init__.py
shreducer_examples/grammars/better_arithmetics.py
shreducer_examples/grammars/better_filters.py
shreducer_examples/grammars/dictionary.py
shreducer_examples/grammars/filter_expressions.py
shreducer_examples/grammars/list_grammar.py
shreducer_examples/grammars/plus_minus_arithmetics.py
shreducer_examples/grammars/type_hints.py
tests/__init__.py
tests/test_arithmetic_generator.py
tests/test_better_arithmetics_grammar.py
tests/test_better_filters.py
tests/test_dictionary_grammar.py
tests/test_filter_expressions_grammar.py
tests/test_grammar.py
tests/test_list_grammar.py
tests/test_parse_tree.py
tests/test_plus_minus_arithmetics.py
tests/test_tokenizers.py
tests/test_type_hints_grammar.py
tests/shreducer_examples_tests/__init__.py
tests/shreducer_examples_tests/test_arithmetic_generator.py
tests/shreducer_examples_tests/test_better_arithmetics_grammar.py
tests/shreducer_examples_tests/test_better_filters.py
tests/shreducer_examples_tests/test_dictionary_grammar.py
